datadocai/__init__.py
datadocai/database/__init__.py
datadocai/metadata/__init__.py
datadocai/metadata/states.py
datadocai/metadata/exporter/__init__.py
datadocai/metadata/exporter/base.py
datadocai/metadata/exporter/datadoc-api.py
datadocai/metadata/exporter/json.py
datadocai/metadata/exporter/open-metadata.py
datadocai/metadata/exporter/trino.py
datadocai/models/__init__.py
datadocai/tools/__init__.py
datadocai-0.0.3.dist-info/METADATA
datadocai-0.0.3.dist-info/WHEEL
datadocai-0.0.3.dist-info/top_level.txt
datadocai-0.0.3.dist-info/RECORD
